{"py/object": "rasa_core.featurizers.MaxHistoryTrackerFeaturizer", "max_history": 4, "remove_duplicates": true, "state_featurizer": {"py/object": "rasa_core.featurizers.BinarySingleStateFeaturizer", "input_state_map": {"entity_location": 4, "intent_acknowledge": 0, "intent_goodbye": 1, "intent_greet": 2, "intent_inform": 3, "prev_action_back": 13, "prev_action_deactivate_form": 9, "prev_action_default_ask_affirmation": 11, "prev_action_default_ask_rephrase": 12, "prev_action_default_fallback": 8, "prev_action_listen": 6, "prev_action_restart": 7, "prev_action_revert_fallback_events": 10, "prev_action_weather": 17, "prev_utter_acknowledge_reply": 19, "prev_utter_action_fallback": 18, "prev_utter_ask_location": 16, "prev_utter_goodbye": 15, "prev_utter_greet": 14, "slot_location_0": 5}, "num_features": 20, "slot_feature_len": 1, "user_feature_len": 5}, "use_intent_probabilities": false}